randomizer/__init__.py
randomizer/controller.py
randomizer/gui.py
randomizer/model.py
randomizer/assets/frame0/button_1.png
randomizer/assets/frame0/button_2.png
randomizer/assets/frame0/button_3.png
randomizer/assets/frame0/button_4.png
randomizer/assets/frame0/entry_1.png
randomizer/assets/frame0/entry_2.png
randomizer/assets/frame0/image_1.png
randomizer/assets/frame0/image_2.png
randomizer/assets/frame0/image_3.png
randomizer/assets/frame0/image_4.png
randomizer_package-0.6.0.dist-info/LICENSE
randomizer_package-0.6.0.dist-info/METADATA
randomizer_package-0.6.0.dist-info/WHEEL
randomizer_package-0.6.0.dist-info/entry_points.txt
randomizer_package-0.6.0.dist-info/top_level.txt
randomizer_package-0.6.0.dist-info/RECORD
