Metadata-Version: 2.1
Name: randomizer-package
Version: 0.6.0
Summary: A randomizer GUI application for generating random outputs.
Home-page: https://github.com/NBlancs/randomizer_nblancs
Author: Nblancs
Author-email: noeljhumel.blanco@1.ustp.edu.ph
Classifier: Programming Language :: Python :: 3
Classifier: License :: OSI Approved :: MIT License
Requires-Python: >=3.6
License-File: LICENSE
